mgraph_ai/__init__.py
mgraph_ai/graphviz_mgraph_ai/__init__.py
mgraph_ai/graphviz_mgraph_ai/fastapi/MGraph_AI_Serverless__Fast_API.py
mgraph_ai/graphviz_mgraph_ai/fastapi/__init__.py
mgraph_ai/graphviz_mgraph_ai/lambdas/__init__.py
mgraph_ai/graphviz_mgraph_ai/lambdas/handler.py
mgraph_ai/graphviz_mgraph_ai/start-local-server.sh
mgraph_ai/utils/Version.py
mgraph_ai/utils/__init__.py
mgraph_ai/version
mgraph_ai-0.14.0.dist-info/LICENSE
mgraph_ai-0.14.0.dist-info/METADATA
mgraph_ai-0.14.0.dist-info/WHEEL
mgraph_ai-0.14.0.dist-info/RECORD
