Metadata-Version: 2.3
Name: mgraph_ai
Version: 0.14.0
Summary: MGraph-AI
License: Apache 2.0
Author: Dinis Cruz
Author-email: dinis.cruz@owasp.org
Requires-Python: >=3.11,<4.0
Classifier: License :: Other/Proprietary License
Classifier: Programming Language :: Python :: 3
Classifier: Programming Language :: Python :: 3.11
Classifier: Programming Language :: Python :: 3.12
Classifier: Programming Language :: Python :: 3.13
Requires-Dist: osbot-utils
Project-URL: Homepage, https://github.com/the-cyber-boardroom/MGraph-AI
Project-URL: Repository, https://github.com/the-cyber-boardroom/MGraph-AI
